kmcpy/__init__.py
kmcpy/_version.py
kmcpy/fitting.py
kmcpy/cli/gui_wrapper.py
kmcpy/cli/run_kmc.py
kmcpy/event/__init__.py
kmcpy/event/event.py
kmcpy/event/event_generator.py
kmcpy/event/modern_event_generator.py
kmcpy/external/__init__.py
kmcpy/external/cif.py
kmcpy/external/local_env.py
kmcpy/external/structure.py
kmcpy/io/__init__.py
kmcpy/io/config_io.py
kmcpy/io/data_loader.py
kmcpy/io/io.py
kmcpy/models/__init__.py
kmcpy/models/cluster.py
kmcpy/models/composite_lce_model.py
kmcpy/models/local_cluster_expansion.py
kmcpy/models/model.py
kmcpy/models/parameters.py
kmcpy/models/fitting/fitter.py
kmcpy/simulator/__init__.py
kmcpy/simulator/condition.py
kmcpy/simulator/config.py
kmcpy/simulator/kmc.py
kmcpy/simulator/state.py
kmcpy/simulator/tracker.py
kmcpy/structure/__init__.py
kmcpy/structure/basis.py
kmcpy/structure/comparator.py
kmcpy/structure/lattice_structure.py
kmcpy/structure/local_environment_comparator.py
kmcpy/structure/local_lattice_structure.py
kmcpy/structure/vacancy.py
kmcpy/tools/gather_kmc_data.py
kmcpy/tools/gather_mc_data.py
kmcpy/tools/get_data.py
kmcpy-0.2.3.dist-info/licenses/LICENSE
kmcpy-0.2.3.dist-info/METADATA
kmcpy-0.2.3.dist-info/WHEEL
kmcpy-0.2.3.dist-info/entry_points.txt
kmcpy-0.2.3.dist-info/top_level.txt
kmcpy-0.2.3.dist-info/RECORD
