Metadata-Version: 2.4
Name: kmcpy
Version: 0.2.3
Summary: Kinetic Monte Carlo Simulation using Python (kMCpy)
Author-email: kMCpy Development Team <dengzeyu@gmail.com>
Maintainer-email: Zeyu Deng <dengzeyu@gmail.com>, Weihang Xie <david.xie1998@gmail.com>, Pieremanuele Canepa <pieremanuele.canepa@gmail.com>
License: MIT License
Project-URL: Homepage, https://github.com/caneparesearch/kmcpy
Project-URL: Repository, https://github.com/caneparesearch/kmcpy
Project-URL: Issues, https://github.com/caneparesearch/kmcpy/issues
Project-URL: Documentation, https://kmcpy.readthedocs.io/
Keywords: kinetic monte carlo,kmc,simulation,materials science,condensed matter physics,chemistry
Classifier: Development Status :: 4 - Beta
Classifier: Intended Audience :: Science/Research
Classifier: Intended Audience :: Developers
Classifier: License :: OSI Approved :: MIT License
Classifier: Programming Language :: Python :: 3
Classifier: Programming Language :: Python :: 3.11
Classifier: Programming Language :: Python :: 3.12
Classifier: Programming Language :: Python :: 3.13
Classifier: Operating System :: OS Independent
Classifier: Topic :: Scientific/Engineering :: Chemistry
Classifier: Topic :: Scientific/Engineering :: Physics
Classifier: Topic :: Software Development :: Libraries :: Python Modules
Requires-Python: >=3.11
License-File: LICENSE
Requires-Dist: glob2>=0.7
Requires-Dist: joblib>=1.5.1
Requires-Dist: numba>=0.61.2
Requires-Dist: pymatgen>=2025.5.2
Requires-Dist: pyyaml>=6.0.2
Requires-Dist: scikit-learn>=1.6.1
Provides-Extra: dev
Requires-Dist: pytest>=8.0; extra == "dev"
Requires-Dist: pytest-cov; extra == "dev"
Provides-Extra: doc
Requires-Dist: sphinx>=7.0; extra == "doc"
Requires-Dist: furo; extra == "doc"
Requires-Dist: nbsphinx; extra == "doc"
Requires-Dist: sphinx-autodoc-typehints; extra == "doc"
Requires-Dist: myst-parser; extra == "doc"
Requires-Dist: tqdm; extra == "doc"
Requires-Dist: psutil; extra == "doc"
Provides-Extra: gui
Requires-Dist: gooey; extra == "gui"
Dynamic: license-file
